<annotation verified="yes">
	<folder>images</folder>
	<filename>222027180-29075341-7411-47d7-b530-5d391ff54f96.jpg</filename>
	<path>/home/r/Рабочий_стол/Python/dave_grohl_detection/images/222027180-29075341-7411-47d7-b530-5d391ff54f96.jpg</path>
	<source>
		<database>Unknown</database>
	</source>
	<size>
		<width>885</width>
		<height>560</height>
		<depth>3</depth>
	</size>
	<segmented>0</segmented>
	<object>
		<name>Dave Grohl</name>
		<pose>Unspecified</pose>
		<truncated>1</truncated>
		<difficult>0</difficult>
		<bndbox>
			<xmin>248</xmin>
			<ymin>8</ymin>
			<xmax>580</xmax>
			<ymax>560</ymax>
		</bndbox>
	</object>
</annotation>
