<annotation verified="yes">
	<folder>images</folder>
	<filename>920x920.jpg</filename>
	<path>/home/r/Рабочий_стол/Python/dave_grohl_detection/images/920x920.jpg</path>
	<source>
		<database>Unknown</database>
	</source>
	<size>
		<width>920</width>
		<height>613</height>
		<depth>3</depth>
	</size>
	<segmented>0</segmented>
	<object>
		<name>Dave Grohl</name>
		<pose>Unspecified</pose>
		<truncated>1</truncated>
		<difficult>0</difficult>
		<bndbox>
			<xmin>307</xmin>
			<ymin>133</ymin>
			<xmax>694</xmax>
			<ymax>613</ymax>
		</bndbox>
	</object>
</annotation>
